harp/devices/behavior/__init__.py
harp/devices/behavior/device.yml
harp/devices/behavior/harpdevice.py
harp_behavior-0.1.0a4.dist-info/WHEEL
harp_behavior-0.1.0a4.dist-info/METADATA
harp_behavior-0.1.0a4.dist-info/RECORD
