Metadata-Version: 2.3
Name: harp-behavior
Version: 0.1.0a4
Summary: This is a generated Harp device Python interface that interacts with the Harp protocol.
Keywords: python,harp
Author: Hardware and Software Platform, Champalimaud Foundation
Author-email: Hardware and Software Platform, Champalimaud Foundation <software@research.fchampalimaud.org>
Requires-Dist: harp-serial==0.4.0
Requires-Python: >=3.9, <4.0
Project-URL: Bug Tracker, https://github.com/fchampalimaud/harp.devices/issues
Project-URL: Documentation, https://fchampalimaud.github.io/pyharp/harp.behavior/
Project-URL: Repository, https://github.com/fchampalimaud/harp.devices/
